qbraid_qir/__init__.py
qbraid_qir/_version.py
qbraid_qir/exceptions.py
qbraid_qir/module.py
qbraid_qir/py.typed
qbraid_qir/serialization.py
qbraid_qir/visitor.py
qbraid_qir/cirq/__init__.py
qbraid_qir/cirq/convert.py
qbraid_qir/cirq/elements.py
qbraid_qir/cirq/exceptions.py
qbraid_qir/cirq/opsets.py
qbraid_qir/cirq/passes.py
qbraid_qir/cirq/qir_target_gateset.py
qbraid_qir/cirq/visitor.py
qbraid_qir/profiles/__init__.py
qbraid_qir/profiles/core.py
qbraid_qir/qasm3/__init__.py
qbraid_qir/qasm3/convert.py
qbraid_qir/qasm3/elements.py
qbraid_qir/qasm3/exceptions.py
qbraid_qir/qasm3/maps.py
qbraid_qir/qasm3/visitor.py
qbraid_qir/squin/__init__.py
qbraid_qir/squin/exceptions.py
qbraid_qir/squin/maps.py
qbraid_qir/squin/visitor.py
qbraid_qir-0.5.0.dist-info/licenses/LICENSE
qbraid_qir-0.5.0.dist-info/METADATA
qbraid_qir-0.5.0.dist-info/WHEEL
qbraid_qir-0.5.0.dist-info/top_level.txt
qbraid_qir-0.5.0.dist-info/RECORD
