Metadata-Version: 2.4
Name: qbraid-qir
Version: 0.5.0
Summary: qBraid-SDK extension providing support for QIR conversions.
Author: qBraid Development Team
Author-email: contact@qbraid.com
License-Expression: Apache-2.0
Project-URL: Homepage, https://github.com/qBraid/qbraid-qir
Project-URL: Documentation, https://docs.qbraid.com/qir
Project-URL: Bug Tracker, https://github.com/qBraid/qbraid-qir/issues
Project-URL: Discord, https://discord.gg/TPBU2sa8Et
Project-URL: Launch on Lab, https://account.qbraid.com/?gitHubUrl=https://github.com/qBraid/qbraid-qir.git
Keywords: qbraid,quantum,qir,llvm,cirq,openqasm
Classifier: Development Status :: 5 - Production/Stable
Classifier: Intended Audience :: Developers
Classifier: Intended Audience :: Science/Research
Classifier: Natural Language :: English
Classifier: Programming Language :: Python
Classifier: Programming Language :: Python :: 3
Classifier: Programming Language :: Python :: 3.10
Classifier: Programming Language :: Python :: 3.11
Classifier: Programming Language :: Python :: 3.12
Classifier: Programming Language :: Python :: 3.13
Classifier: Programming Language :: Python :: 3 :: Only
Classifier: Typing :: Typed
Classifier: Topic :: Scientific/Engineering
Classifier: Topic :: Scientific/Engineering :: Physics
Requires-Python: >=3.10
License-File: LICENSE
Requires-Dist: pyqir<0.11.0,>=0.10.0
Provides-Extra: cirq
Requires-Dist: cirq-core<1.6.0,>=1.3.0; extra == "cirq"
Provides-Extra: qasm3
Requires-Dist: pyqasm<1.1.0,>=0.4.0; extra == "qasm3"
Requires-Dist: numpy; extra == "qasm3"
Provides-Extra: squin
Requires-Dist: kirin-toolchain>=0.17.33; extra == "squin"
Requires-Dist: bloqade-circuit>=0.9.1; extra == "squin"
Provides-Extra: test
Requires-Dist: qbraid<0.11.0,>=0.9.0; extra == "test"
Requires-Dist: pytest; extra == "test"
Requires-Dist: pytest-cov; extra == "test"
Requires-Dist: autoqasm>=0.1.0; extra == "test"
Requires-Dist: cudaq; extra == "test"
Dynamic: license-file
